MANIFEST.in
README.md
setup.cfg
setup.py
deform_foundation/__init__.py
deform_foundation/resources.py
deform_foundation/widget.py
deform_foundation.egg-info/PKG-INFO
deform_foundation.egg-info/SOURCES.txt
deform_foundation.egg-info/dependency_links.txt
deform_foundation.egg-info/not-zip-safe
deform_foundation.egg-info/requires.txt
deform_foundation.egg-info/top_level.txt
deform_foundation/static/js/jquery-chosen/chosen-sprite.png
deform_foundation/static/js/jquery-chosen/chosen.css
deform_foundation/static/js/jquery-chosen/chosen.jquery.min.js
deform_foundation/templates/chosen_multiple.pt
deform_foundation/templates/chosen_optgroup.pt
deform_foundation/templates/chosen_single.pt
deform_foundation/templates/form.pt
deform_foundation/templates/mapping.pt
deform_foundation/templates/mapping_item.pt
deform_foundation/templates/sequence.pt
deform_foundation/templates/sequence_item.pt