Metadata-Version: 1.1
Name: deform-foundation
Version: 0.5.5
Summary: A template package for deform that uses Foundation
Home-page: http://bitbucket.org/ixmatus/deform-foundation
Author: Parnell Springmeyer
Author-email: parnell@ixmat.us
License: PSF
Platform: UNKNOWN
Classifier: Intended Audience :: Developers
Classifier: License :: OSI Approved :: Python Software Foundation License
Classifier: Programming Language :: Python
Classifier: Topic :: Software Development :: Libraries :: Python Modules
